multiple_auth/__init__.py
multiple_auth/admin.py
multiple_auth/apps.py
multiple_auth/backends.py
multiple_auth/models.py
multiple_auth/tests.py
multiple_auth/views.py
multiple_auth/migrations/__init__.py
django_multiple_authentication-2.0.5.dist-info/LICENCE
django_multiple_authentication-2.0.5.dist-info/METADATA
django_multiple_authentication-2.0.5.dist-info/WHEEL
django_multiple_authentication-2.0.5.dist-info/top_level.txt
django_multiple_authentication-2.0.5.dist-info/RECORD
