Metadata-Version: 2.1
Name: django-multiple-authentication
Version: 2.0.5
Summary: Enables developers to implement login with email or username or any other field on your user model in django
Home-page: https://github.com/korededavid/django-multiple-authentication
Author: Oluwashola David
Author-email: koredeoluwashola@gmail.com
Maintainer: Oluwashola David
Maintainer-email: koredeoluwashola@gmail.com
License: MIT LICENCE
Keywords: django authenticate python authentication python login user username email django-multiple-auth multiple-auth  multiple auth
Classifier: Development Status :: 4 - Beta
Classifier: Environment :: Web Environment
Classifier: Framework :: Django
Classifier: Framework :: Django :: 3.0
Classifier: Framework :: Django :: 3.1
Classifier: Framework :: Django :: 3.2
Classifier: Framework :: Django :: 4.0
Classifier: Intended Audience :: Developers
Classifier: License :: OSI Approved :: MIT License
Classifier: Operating System :: OS Independent
Classifier: Programming Language :: Python :: 3
Classifier: Programming Language :: Python :: 3 :: Only
Classifier: Programming Language :: Python :: 3.6
Classifier: Programming Language :: Python :: 3.7
Classifier: Programming Language :: Python :: 3.8
Classifier: Programming Language :: Python :: 3.9
Classifier: Programming Language :: Python :: 3.10
Classifier: Programming Language :: Python :: Implementation :: CPython
Classifier: Topic :: Software Development :: Libraries :: Application Frameworks
Classifier: Topic :: Software Development :: Libraries :: Python Modules
Requires-Python: >=3.6
License-File: LICENCE
